{
  "basic": {
    "age": 5,
    "residence": 4,
    "marry": 5,
    "education": 11,
    "occupation": 12
  },
  "property": {
    "household": 5,
  },
  "PBOC": {
    "bank": 4,
    "loan": 4,
    "loan_card": 6,
    "bank_check": 4,
    "back_self_check": 2,
    "finance": 4,
    "loan_unpaid": 5,
    "loan_card_unpaid": 5,
    "loan_card_paid": 6
  },
  "PBOC_history": {
    "loan_month": 5,
    "loan_card_month": 5
  },
  "ability": {
    "AUM1": 6,
    "AUM2": 6,
    "DBR": 6,
    "LTV": 5,
    "market_percent": 6,
  }
}
